downloadbook/__init__.py
downloadbook/functions.py
downloadbook-0.0.1.dist-info/LICENSE
downloadbook-0.0.1.dist-info/METADATA
downloadbook-0.0.1.dist-info/WHEEL
downloadbook-0.0.1.dist-info/top_level.txt
downloadbook-0.0.1.dist-info/RECORD
