Metadata-Version: 2.1
Name: downloadbook
Version: 0.0.1
Summary: download books
Home-page: https://github.com/zerenlu/downloadbook
Author: zerenlu
Author-email: zeren.lu@gmail.com
License: MIT Licence
Keywords: pip,download,book,zerenl
Platform: any
Requires-Dist: requests
Requires-Dist: bs4
